circhemy/__init__.py
circhemy/circhemy_cli.py
circhemy/circhemy_web.py
circhemy/cli/__init__.py
circhemy/cli/cli.py
circhemy/common/__init__.py
circhemy/common/util.py
circhemy/data/circhemy_convert.results
circhemy/data/circhemy_query.results
circhemy/web/__init__.py
circhemy/web/svg.py
circhemy/web/web.py
circhemy/web/favicon/android-chrome-192x192.png
circhemy/web/favicon/android-chrome-384x384.png
circhemy/web/favicon/android-chrome-512x512.png
circhemy/web/favicon/android-icon-144x144.png
circhemy/web/favicon/android-icon-192x192.png
circhemy/web/favicon/android-icon-36x36.png
circhemy/web/favicon/android-icon-48x48.png
circhemy/web/favicon/android-icon-72x72.png
circhemy/web/favicon/android-icon-96x96.png
circhemy/web/favicon/apple-icon-114x114.png
circhemy/web/favicon/apple-icon-120x120.png
circhemy/web/favicon/apple-icon-144x144.png
circhemy/web/favicon/apple-icon-152x152.png
circhemy/web/favicon/apple-icon-180x180.png
circhemy/web/favicon/apple-icon-57x57.png
circhemy/web/favicon/apple-icon-60x60.png
circhemy/web/favicon/apple-icon-72x72.png
circhemy/web/favicon/apple-icon-76x76.png
circhemy/web/favicon/apple-icon-precomposed.png
circhemy/web/favicon/apple-icon.png
circhemy/web/favicon/apple-touch-icon.png
circhemy/web/favicon/browserconfig.xml
circhemy/web/favicon/favicon-16x16.png
circhemy/web/favicon/favicon-32x32.png
circhemy/web/favicon/favicon-96x96.png
circhemy/web/favicon/favicon.ico
circhemy/web/favicon/manifest.json
circhemy/web/favicon/ms-icon-144x144.png
circhemy/web/favicon/ms-icon-150x150.png
circhemy/web/favicon/ms-icon-310x310.png
circhemy/web/favicon/ms-icon-70x70.png
circhemy/web/favicon/site.webmanifest
circhemy/web/fonts/fira-mono-v14-latin-regular.eot
circhemy/web/fonts/fira-mono-v14-latin-regular.svg
circhemy/web/fonts/fira-mono-v14-latin-regular.ttf
circhemy/web/fonts/fira-mono-v14-latin-regular.woff
circhemy/web/fonts/fira-mono-v14-latin-regular.woff2
circhemy/web/fonts/fira-sans-v16-latin-500.eot
circhemy-0.1.0.dist-info/METADATA
circhemy-0.1.0.dist-info/WHEEL
circhemy-0.1.0.dist-info/entry_points.txt
circhemy-0.1.0.dist-info/top_level.txt
circhemy-0.1.0.dist-info/RECORD
