Metadata-Version: 2.1
Name: circhemy
Version: 0.1.0
Summary: circhemy - The alchemy of circular RNA ID conversion
Home-page: https://github.com/jakobilab/circhemy
Author: Tobias Jakobi
Author-email: tjakobi@arizona.edu
License: GNU General Public License (GPL)
Project-URL: Bug Reports, https://github.com/jakobilab/circhemy/issues
Project-URL: Jakobi Lab, https://jakobilab.org
Project-URL: Source, https://github.com/jakobilab/circhemy
Project-URL: Documentation, https://circhemy.jakobilab.org
Project-URL: circtools circRNA analytics, https://github.com/jakobilab/circtools
Keywords: circRNA,circular RNA (circRNA) naming,circular RNA (circRNA) bioinformatics,circular RNA (circRNA) ID conversion,circular RNA (circRNA) database
Classifier: Development Status :: 4 - Beta
Classifier: Intended Audience :: Science/Research
Classifier: Topic :: Scientific/Engineering :: Bio-Informatics
Classifier: Programming Language :: Python :: 3.8
Classifier: Programming Language :: Python :: 3.9
Classifier: Programming Language :: Python :: 3.10
Classifier: Programming Language :: Python :: 3.11
Classifier: Programming Language :: Python :: 3.12
Requires-Python: >=3.8
Requires-Dist: argparse
Provides-Extra: web
Requires-Dist: nicegui[highcharts] >=1.4.22 ; extra == 'web'
Requires-Dist: feedparser >=6.0.11 ; extra == 'web'
Requires-Dist: python-dateutil >=2.9.0.post0 ; extra == 'web'
Requires-Dist: fastapi <0.110.0,>=0.109.1 ; extra == 'web'
Requires-Dist: pydantic >=2.6.4 ; extra == 'web'
Requires-Dist: Pygments >=2.17.2 ; extra == 'web'
